_chronogram.cp38-win_amd64.pyd
_chronogram_avx.cp38-win_amd64.pyd
_chronogram_avx2.cp38-win_amd64.pyd
chronogram/__init__.py
chronogram-0.2.0.dist-info/METADATA
chronogram-0.2.0.dist-info/WHEEL
chronogram-0.2.0.dist-info/top_level.txt
chronogram-0.2.0.dist-info/RECORD
