Metadata-Version: 2.1
Name: chronogram
Version: 0.2.0
Summary: Chrono-gram, the diachronic word embedding model based on Word2vec Skip-gram with Chebyshev approximation
Home-page: https://github.com/bab2min/chronogram
Author: bab2min
Author-email: bab2min@gmail.com
License: MIT License
Keywords: NLP,Word2vec,Word Embedding
Classifier: Development Status :: 3 - Alpha
Classifier: Intended Audience :: Information Technology
Classifier: Intended Audience :: Science/Research
Classifier: Topic :: Software Development :: Libraries
Classifier: Topic :: Text Processing :: Linguistic
Classifier: Topic :: Scientific/Engineering :: Information Analysis
Classifier: License :: OSI Approved :: MIT License
Classifier: Programming Language :: Python :: 3
Classifier: Programming Language :: C++
Classifier: Operating System :: Microsoft :: Windows :: Windows Vista
Classifier: Operating System :: Microsoft :: Windows :: Windows 7
Classifier: Operating System :: Microsoft :: Windows :: Windows 8
Classifier: Operating System :: Microsoft :: Windows :: Windows 8.1
Classifier: Operating System :: Microsoft :: Windows :: Windows 10
Classifier: Operating System :: POSIX
Requires-Dist: py-cpuinfo
